odoo/addons/l10n_th_tier_department_demo/README.rst
odoo/addons/l10n_th_tier_department_demo/__init__.py
odoo/addons/l10n_th_tier_department_demo/__manifest__.py
odoo/addons/l10n_th_tier_department_demo/data/hr_expense_tier_definition.xml
odoo/addons/l10n_th_tier_department_demo/data/purchase_request_tier_definition.xml
odoo/addons/l10n_th_tier_department_demo/i18n/l10n_th_tier_department_demo.pot
odoo/addons/l10n_th_tier_department_demo/readme/CONTRIBUTORS.md
odoo/addons/l10n_th_tier_department_demo/readme/DESCRIPTION.md
odoo/addons/l10n_th_tier_department_demo/static/description/icon.png
odoo/addons/l10n_th_tier_department_demo/static/description/index.html
odoo_addon_l10n_th_tier_department_demo-18.0.1.0.0.2.dist-info/METADATA
odoo_addon_l10n_th_tier_department_demo-18.0.1.0.0.2.dist-info/WHEEL
odoo_addon_l10n_th_tier_department_demo-18.0.1.0.0.2.dist-info/top_level.txt
odoo_addon_l10n_th_tier_department_demo-18.0.1.0.0.2.dist-info/RECORD
