Metadata-Version: 2.1
Name: odoo-addon-l10n_th_tier_department_demo
Version: 18.0.1.0.0.2
Requires-Python: >=3.10
Requires-Dist: odoo-addon-hr_expense_advance_clearing==18.0.*
Requires-Dist: odoo-addon-hr_expense_tier_validation==18.0.*
Requires-Dist: odoo-addon-l10n_th_tier_department==18.0.*
Requires-Dist: odoo-addon-purchase_request_tier_validation==18.0.*
Requires-Dist: odoo==18.0.*
Summary: Thai Localization - Tier Department Level Demo
Home-page: https://github.com/OCA/l10n-thailand
License: AGPL-3
Author: Ecosoft, Odoo Community Association (OCA)
Author-email: support@odoo-community.org
Classifier: Programming Language :: Python
Classifier: Framework :: Odoo
Classifier: Framework :: Odoo :: 18.0
Classifier: License :: OSI Approved :: GNU Affero General Public License v3
Classifier: Development Status :: 3 - Alpha
